dwave_sapi_dimod/__init__.py
dwave_sapi_dimod/composites.py
dwave_sapi_dimod/samplers.py
dwave_sapi_dimod-0.3.1.dist-info/DESCRIPTION.rst
dwave_sapi_dimod-0.3.1.dist-info/METADATA
dwave_sapi_dimod-0.3.1.dist-info/RECORD
dwave_sapi_dimod-0.3.1.dist-info/WHEEL
dwave_sapi_dimod-0.3.1.dist-info/metadata.json
dwave_sapi_dimod-0.3.1.dist-info/top_level.txt
