Metadata-Version: 2.0
Name: dwave-sapi-dimod
Version: 0.3.1
Summary: UNKNOWN
Home-page: UNKNOWN
Author: UNKNOWN
Author-email: UNKNOWN
License: Apache 2.0
Platform: UNKNOWN
Requires-Dist: dimod (>=0.3.0)
Requires-Dist: dwave-sapi2
